streamlit_contrib_clipboard/__init__.py
streamlit_contrib_clipboard/copy_to_clipboard.py
streamlit_contrib_clipboard/frontend/build/index.html
streamlit_contrib_clipboard/frontend/build/index.js
streamlit_contrib_clipboard-0.1.5.dist-info/licenses/LICENSE
streamlit_contrib_clipboard-0.1.5.dist-info/METADATA
streamlit_contrib_clipboard-0.1.5.dist-info/WHEEL
streamlit_contrib_clipboard-0.1.5.dist-info/top_level.txt
streamlit_contrib_clipboard-0.1.5.dist-info/RECORD
