Metadata-Version: 2.4
Name: streamlit-contrib-clipboard
Version: 0.1.5
Summary: A Streamlit component to copy text to clipboard, even in iframed apps.
Home-page: https://github.com/om-pramod/streamlit-contrib-clipboard
Author: Omkar Pramod Hankare
Author-email: ompramod9921@gmail.com
License: MIT
Classifier: Programming Language :: Python :: 3.8
Classifier: Programming Language :: Python :: 3.9
Classifier: Programming Language :: Python :: 3.10
Classifier: Programming Language :: Python :: 3.11
Classifier: Operating System :: OS Independent
Requires-Python: >=3.8
License-File: LICENSE
Requires-Dist: streamlit>=1.20.0
Dynamic: author
Dynamic: author-email
Dynamic: classifier
Dynamic: description
Dynamic: description-content-type
Dynamic: home-page
Dynamic: license
Dynamic: license-file
Dynamic: requires-dist
Dynamic: requires-python
Dynamic: summary
